[{"hc-key": "at","value": 44.2811881188

 },
{"hc-key": "be","value": 83.0639658849

},
{"hc-key": "bg","value": 90.0698412698
}, 
{"hc-key": "ch","value": 19.2895752896
},
{"hc-key": "cy","value": 6.1935483871
},
{"hc-key": "cz","value": 97.2085561497
},
{"hc-key": "de","value": 251.8218181818

},
{"hc-key": "dk","value": 78.3551136364

},
{"hc-key": "ee","value": 44.4463768116
},
{"hc-key": "es","value": 266.6317204301

},
{"hc-key": "fi","value": 87.7866666667

},
{"hc-key": "fr","value": 572.5375

},
{"hc-key": "hr","value": 51.7799352751
},
{"hc-key": "hu","value": 106.9321428571
},
{"hc-key": "ie","value": 48.048346056

},
{"hc-key": "it","value": 0.4966777409

},
{"hc-key": "li","value": 243.3756345178
},
{"hc-key": "lt","value": 0.0286532951
},
{"hc-key": "lu","value": 51.0310077519

},
{"hc-key": "lv","value": 4.3896499239
},
{"hc-key": "nl","value": 82.0797342193

},
{"hc-key": "no","value": 2.46484375

},
{"hc-key": "pl","value": 54
},
{"hc-key": "pt","value": 88.8657407407

},
{"hc-key": "ro","value": 508.2452229299
},
{"hc-key": "se","value": 105.2190305206
},
{"hc-key": "si","value": 700.0466666667
},
{ "hc-key": "sk","value": 57.5458515284
},
{"hc-key": "gb","value": 28.1710526316

}
]